{"name":"Joseph's Page","tagline":"","body":"<p>\r\nHi there, I am a second term Computer Systems Technology student at BCIT. This page contains a sample of my work and will continue to grow as I work on more projects and gain more experience\r\n</p>\r\n[Tic-Tac-Toe Game](TicTacToe/index.html)<br/>\r\n[Animated House Canvas](HouseCanvas/index.html)<br/>\r\n[Chinese Zodiac Site](ChineseZodiac/index.html)","google":"","note":"Don't delete this file! It's used internally to help with page regeneration."}